pre_notifier/__init__.py
pre_notifier/config.ini
pre_notifier/pre_notifier.py
pre_notifier-0.1.20.dist-info/entry_points.txt
pre_notifier-0.1.20.dist-info/WHEEL
pre_notifier-0.1.20.dist-info/METADATA
pre_notifier-0.1.20.dist-info/RECORD
